kaictl.py
kaictl-0.1.2.dist-info/METADATA
kaictl-0.1.2.dist-info/WHEEL
kaictl-0.1.2.dist-info/entry_points.txt
kaictl-0.1.2.dist-info/top_level.txt
kaictl-0.1.2.dist-info/RECORD
